MANIFEST.in
README.md
build.py
pyproject.toml
requirements-dev.txt
requirements.txt
setup.py
test.py
license_plate_recognition.egg-info/PKG-INFO
license_plate_recognition.egg-info/SOURCES.txt
license_plate_recognition.egg-info/dependency_links.txt
license_plate_recognition.egg-info/requires.txt
license_plate_recognition.egg-info/top_level.txt
lpr/__init__.py
lpr/base.py
lpr/lpr.py
lpr/tesseract.py
lpr/characters/__init__.py
lpr/characters/definition.py
lpr/characters/detection.py
lpr/definition/__init__.py
lpr/definition/colors.py
lpr/definition/dimensions.py
lpr/interface/__init__.py
lpr/interface/visualize.py
lpr/plates/__init__.py
lpr/plates/definition.py
lpr/plates/detection.py
lpr/process/image.py
lpr/process/model.py
lpr/process/preparation.py
lpr/source/dataset/classifications.txt
lpr/source/dataset/flattened_images.txt
lpr/source/tesseract/ambiguous_words.exe
lpr/source/tesseract/classifier_tester.exe
lpr/source/tesseract/cntraining.exe
lpr/source/tesseract/combine_lang_model.exe
lpr/source/tesseract/combine_tessdata.exe
lpr/source/tesseract/dawg2wordlist.exe
lpr/source/tesseract/loc.4da92171.tesseract.libtesseract-local.dll
lpr/source/tesseract/lstmeval.exe
lpr/source/tesseract/lstmtraining.exe
lpr/source/tesseract/mftraining.exe
lpr/source/tesseract/pvt.cppan.demo.behdad.harfbuzz-1.9.0.dll
lpr/source/tesseract/pvt.cppan.demo.bzip2-1.0.6.dll
lpr/source/tesseract/pvt.cppan.demo.cairographics.cairo-1.15.14.dll
lpr/source/tesseract/pvt.cppan.demo.danbloomberg.leptonica-1.76.0.dll
lpr/source/tesseract/pvt.cppan.demo.expat-2.2.6.dll
lpr/source/tesseract/pvt.cppan.demo.freedesktop.fontconfig.fontconfig-2.13.0.dll
lpr/source/tesseract/pvt.cppan.demo.freetype-2.9.1.dll
lpr/source/tesseract/pvt.cppan.demo.gnome.glib.glib-2.56.1.dll
lpr/source/tesseract/pvt.cppan.demo.gnome.glib.gobject-2.56.1.dll
lpr/source/tesseract/pvt.cppan.demo.gnome.pango.pango-1.42.3.dll
lpr/source/tesseract/pvt.cppan.demo.gnome.pango.pangocairo-1.42.3.dll
lpr/source/tesseract/pvt.cppan.demo.gnome.pango.pangoft2-1.42.3.dll
lpr/source/tesseract/pvt.cppan.demo.gnu.fribidi.fribidi-1.0.5.dll
lpr/source/tesseract/pvt.cppan.demo.gnu.gettext.intl-0.19.8.dll
lpr/source/tesseract/pvt.cppan.demo.gnu.iconv.libcharset-1.15.0.dll
