Metadata-Version: 2.1
Name: license-plate-recognition
Version: 1.3.1
Summary: A module powered by Machine-Learning algorithms designed to detect, recognize and read license plates from car pictures. The module is flexible and equipped with objects and functions to make the process_thresh of LPR easy and fast. The program creates an artificial k nearest neighbour model that detects and reads licensee plate from a car image.
Home-page: https://github.com/Shahaf-F-S/license-plate-recognition
Author: Shahaf Frank-Shapir
Author-email: shahaffrs@gmail.com
License: MIT
Classifier: Intended Audience :: Developers
Classifier: License :: OSI Approved :: MIT License
Classifier: Programming Language :: Python
Classifier: Programming Language :: Python :: 3
Classifier: Programming Language :: Python :: 3.8
Classifier: Programming Language :: Python :: 3.9
Classifier: Programming Language :: Python :: 3.10
Classifier: Programming Language :: Python :: 3.11
Classifier: Operating System :: OS Independent
Provides-Extra: dev
